psgd_torch/__init__.py
psgd_torch/psgd.py
psgd_torch-0.6.1.dist-info/METADATA
psgd_torch-0.6.1.dist-info/WHEEL
psgd_torch-0.6.1.dist-info/top_level.txt
psgd_torch-0.6.1.dist-info/RECORD
