Metadata-Version: 2.1
Name: psgd_torch
Version: 0.6.1
Requires-Dist: torch
Requires-Dist: opt-einsum
